pyduktape2.cpython-310-aarch64-linux-gnu.so
pyduktape2-0.5.0.dist-info/METADATA
pyduktape2-0.5.0.dist-info/WHEEL
pyduktape2-0.5.0.dist-info/top_level.txt
pyduktape2-0.5.0.dist-info/RECORD
pyduktape2-0.5.0.dist-info/licenses/LICENSE.txt
