Metadata-Version: 2.1
Name: pyduktape2
Version: 0.5.0
Summary: Python integration for the Duktape Javascript interpreter
Home-page: https://github.com/phith0n/pyduktape2
Author: Stefano Dissegna
License: GPL-2.0-only
Keywords: javascript duktape embed
Platform: UNKNOWN
Classifier: Development Status :: 2 - Pre-Alpha
Classifier: Programming Language :: Cython
Classifier: Programming Language :: Python :: 3
Classifier: Programming Language :: JavaScript
Classifier: Topic :: Software Development :: Interpreters
License-File: LICENSE.txt
